LICENSE
MANIFEST.in
README.rst
setup.py
django_jsonis.egg-info/PKG-INFO
django_jsonis.egg-info/SOURCES.txt
django_jsonis.egg-info/dependency_links.txt
django_jsonis.egg-info/requires.txt
django_jsonis.egg-info/top_level.txt
jsonis/__init__.py
jsonis/middleware.py
jsonis/tests.py
jsonis/utils.py
jsonis/views.py
jsonis/jwt/__init__.py
jsonis/jwt/auth_backends.py
jsonis/jwt/middleware.py
jsonis/jwt/utils.py
jsonis/jwt/views.py
jsonis/templatetags/__init__.py
jsonis/templatetags/jsonify.py