Metadata-Version: 1.1
Name: django-jsonis
Version: 0.1.10
Summary: Django JSON Utils
Home-page: https://github.com/rychlis/django-jsonis
Author: Tomas Rychlik
Author-email: rychlis@rychlis.cz
License: MIT
Platform: UNKNOWN
Classifier: Development Status :: 3 - Alpha
Classifier: License :: OSI Approved :: MIT License
Classifier: Intended Audience :: Developers
Classifier: Operating System :: OS Independent
Classifier: Programming Language :: Python
Classifier: Programming Language :: Python :: 2.7
Classifier: Topic :: Software Development :: Libraries
Classifier: Topic :: Software Development :: Libraries :: Python Modules
